lightdown/__init__.py
lightdown/core.py
lightdown/markdown_renderer.py
lightdown/router.py
lightdown/static_handler.py
lightdown/template_engine.py
lightdown-0.1.0.dist-info/licenses/LICENSE
lightdown-0.1.0.dist-info/METADATA
lightdown-0.1.0.dist-info/WHEEL
lightdown-0.1.0.dist-info/top_level.txt
lightdown-0.1.0.dist-info/RECORD
