Metadata-Version: 2.4
Name: lightdown
Version: 0.1.0
Summary: Simplify web framework for build web applications with Markdown
Author-email: Ekin Ilter Varli <ekiniltervarli@gmail.com>
License: MIT
Project-URL: Homepage, https://github.com/eknvarli/lightdown
Requires-Python: >=3.8
License-File: LICENSE
Requires-Dist: markdown
Dynamic: license-file
